kb_python/__init__.py
kb_python/compile.py
kb_python/config.py
kb_python/constants.py
kb_python/count.py
kb_python/extract.py
kb_python/info.txt
kb_python/logging.py
kb_python/main.py
kb_python/ref.py
kb_python/report.py
kb_python/stats.py
kb_python/utils.py
kb_python/validate.py
kb_python/bins/darwin/bustools/LICENSE
kb_python/bins/darwin/bustools/bustools
kb_python/bins/darwin/kallisto/kallisto
kb_python/bins/darwin/kallisto/kallisto_k64
kb_python/bins/darwin/kallisto/kallisto_optoff
kb_python/bins/darwin/kallisto/kallisto_optoff_k64
kb_python/bins/darwin/kallisto/license.txt
kb_python/bins/darwin/m1/bustools/LICENSE
kb_python/bins/darwin/m1/bustools/bustools
kb_python/bins/darwin/m1/kallisto/kallisto
kb_python/bins/darwin/m1/kallisto/kallisto_k64
kb_python/bins/darwin/m1/kallisto/kallisto_optoff
kb_python/bins/darwin/m1/kallisto/kallisto_optoff_k64
kb_python/bins/darwin/m1/kallisto/license.txt
kb_python/bins/linux/bustools/LICENSE
kb_python/bins/linux/bustools/bustools
kb_python/bins/linux/kallisto/kallisto
kb_python/bins/linux/kallisto/kallisto_k64
kb_python/bins/linux/kallisto/kallisto_optoff
kb_python/bins/linux/kallisto/kallisto_optoff_k64
kb_python/bins/linux/kallisto/license.txt
kb_python/bins/windows/bustools/LICENSE
kb_python/bins/windows/bustools/bustools.exe
kb_python/bins/windows/kallisto/kallisto.exe
kb_python/bins/windows/kallisto/kallisto_k64.exe
kb_python/bins/windows/kallisto/kallisto_optoff.exe
kb_python/bins/windows/kallisto/kallisto_optoff_k64.exe
kb_python/bins/windows/kallisto/license.txt
kb_python/dry/__init__.py
kb_python/dry/count.py
kb_python/dry/utils.py
kb_python/report/base.html
kb_python/report/report_basic.ipynb
kb_python/report/report_matrix.ipynb
kb_python/report/css/bootstrap.min.css
kb_python/report/js/bootstrap.min.js
kb_python/report/js/jquery-3.4.1.slim.min.js
kb_python/report/js/plotly-latest.min.js
kb_python/report/js/popper.min.js
kb_python-0.29.5.dist-info/LICENSE
kb_python-0.29.5.dist-info/METADATA
kb_python-0.29.5.dist-info/WHEEL
kb_python-0.29.5.dist-info/entry_points.txt
kb_python-0.29.5.dist-info/top_level.txt
kb_python-0.29.5.dist-info/RECORD
