Metadata-Version: 2.1
Name: kb_python
Version: 0.29.5
Summary: Python wrapper around kallisto | bustools for scRNA-seq analysis
Home-page: https://github.com/pachterlab/kb_python
Author: Kyung Hoi (Joseph) Min
Author-email: phoenixter96@gmail.com
Maintainer: Pachter Lab
Maintainer-email: lpachter@caltech.edu
License: BSD
Keywords: kallisto bustools
Classifier: Development Status :: 5 - Production/Stable
Classifier: Environment :: Console
Classifier: Intended Audience :: Science/Research
Classifier: License :: OSI Approved :: BSD License
Classifier: Operating System :: POSIX :: Linux
Classifier: Operating System :: MacOS
Classifier: Operating System :: Microsoft :: Windows
Classifier: Programming Language :: Python :: 3.8
Classifier: Programming Language :: Python :: 3.9
Classifier: Programming Language :: Python :: 3.10
Classifier: Topic :: Scientific/Engineering :: Bio-Informatics
Classifier: Topic :: Utilities
Requires-Python: >=3.8
License-File: LICENSE
Requires-Dist: anndata >=0.9.2
Requires-Dist: h5py >=2.10.0
Requires-Dist: Jinja2 >2.10.1
Requires-Dist: loompy >=3.0.6
Requires-Dist: nbconvert >=5.6.0
Requires-Dist: nbformat >=4.4.0
Requires-Dist: ngs-tools >=1.8.6
Requires-Dist: numpy >=1.17.2
Requires-Dist: pandas >=1.5.3
Requires-Dist: plotly >=4.5.0
Requires-Dist: requests >=2.22.0
Requires-Dist: scanpy >=1.4.4.post1
Requires-Dist: scikit-learn >=0.21.3
Requires-Dist: typing-extensions >=3.7.4
Requires-Dist: biopython >=1.8
